README.rst
setup.py
txmako/__init__.py
txmako/page.py
txmako/session.py
txmako.egg-info/PKG-INFO
txmako.egg-info/SOURCES.txt
txmako.egg-info/dependency_links.txt
txmako.egg-info/requires.txt
txmako.egg-info/top_level.txt